perfy
