Metadata-Version: 2.1
Name: perfy
Version: 0.26
Summary: Perfy - a lightweight performance tracer for python
Home-page: https://github.com/glebarez/perfy
Author: Gleb Sakhnov
Author-email: gleb.sakhnov@gmail.com
License: MIT
Keywords: profiling,trace,runtime,analysis
Platform: UNKNOWN
Classifier: Development Status :: 5 - Production/Stable
Classifier: Intended Audience :: Developers
Classifier: Topic :: Software Development :: Build Tools
Classifier: License :: OSI Approved :: MIT License
Classifier: Programming Language :: Python :: 3
Classifier: Programming Language :: Python :: 3.4
Classifier: Programming Language :: Python :: 3.5
Classifier: Programming Language :: Python :: 3.6
Classifier: Programming Language :: Python :: 3.7
Requires-Python: >=3.2
